hrim/__init__.py
hrim/__main__.py
hrim/scripts/__init__.py
hrim/scripts/classes.py
hrim/scripts/compiling.py
hrim/scripts/parsing.py
hrim/scripts/utils.py
hrim-0.3.dist-info/METADATA
hrim-0.3.dist-info/WHEEL
hrim-0.3.dist-info/entry_points.txt
hrim-0.3.dist-info/top_level.txt
hrim-0.3.dist-info/RECORD
