Metadata-Version: 2.1
Name: hrim
Version: 0.3
Summary: HRIM command line utility
Home-page: https://github.com/erlerobot/HRIM
Author: UNKNOWN
Author-email: UNKNOWN
License: Apache-2.0
Keywords: HRIM,H-ROS,modular,ros2,robot operating system
Platform: UNKNOWN
Requires-Dist: lxml
